src/__init__.py
src/library.py
src/main.py
normalize_companies_names-1.0.1.dist-info/METADATA
normalize_companies_names-1.0.1.dist-info/WHEEL
normalize_companies_names-1.0.1.dist-info/entry_points.txt
normalize_companies_names-1.0.1.dist-info/RECORD
