Metadata-Version: 2.1
Name: normalize-companies-names
Version: 1.0.1
Summary: 
Author: WillersonAbreu
Author-email: willersonabreu@hotmail.com
Requires-Python: >=3.10,<4.0
Classifier: Programming Language :: Python :: 3
Classifier: Programming Language :: Python :: 3.10
Classifier: Programming Language :: Python :: 3.11
Classifier: Programming Language :: Python :: 3.12
Requires-Dist: click (>=8.1.7,<9.0.0)
Requires-Dist: openpyxl (>=3.1.2,<4.0.0)
Requires-Dist: pandas (>=2.2.1,<3.0.0)
Requires-Dist: thefuzz (>=0.22.1,<0.23.0)
Requires-Dist: wheel (>=0.43.0,<0.44.0)
